{
  "name": "仗义",
  "children": [{
    "name": "仗义",
    "children": [{
      "name": "仗义",
      "children": []
    }, {
      "name": "仗义",
      "children": [{
        "name": "仗义",
        "children": []
      }, {
        "name": "仗义",
        "children": [{
          "name": "仗义",
          "children": [{
            "name": "仗义",
            "children": [{
              "name": "仗义",
              "children": []
            }, {
              "name": "仗义",
              "children": [{
                "name": "仗义",
                "children": []
              }, {
                "name": "仗义",
                "children": [{
                  "name": "仗义",
                  "children": []
                }]
              }, {
                "name": "仗义",
                "children": [{
                  "name": "仗义",
                  "children": []
                }]
              }, {
                "name": "仗义",
                "children": [{
                  "name": "仗义",
                  "children": []
                }]
              }, {
                "name": "仗义",
                "children": [{
                  "name": "仗义",
                  "children": []
                }]
              }]
            }, {
              "name": "仗义",
              "children": [{
                "name": "仗义",
                "children": []
              }]
            }, {
              "name": "仗义",
              "children": [{
                "name": "仗义",
                "children": []
              }]
            }]
          }]
        }, {
          "name": "仗义",
          "children": [{
            "name": "仗义",
            "children": []
          }]
        }]
      }]
    }]
  }, {
    "name": "仗义",
    "children": [{
      "name": "仗义",
      "children": [{
        "name": "仗义",
        "children": [{
          "name": "仗义",
          "children": [{
            "name": "仗义",
            "children": [{
              "name": "仗义",
              "children": []
            }, {
              "name": "仗义",
              "children": [{
                "name": "仗义",
                "children": []
              }]
            }]
          }]
        }, {
          "name": "仗义",
          "children": [{
            "name": "仗义",
            "children": [{
              "name": "仗义",
              "children": [{
                "name": "仗义",
                "children": []
              }, {
                "name": "仗义",
                "children": [{
                  "name": "仗义",
                  "children": []
                }]
              }, {
                "name": "仗义",
                "children": [{
                  "name": "仗义",
                  "children": []
                }]
              }]
            }]
          }]
        }, {
          "name": "仗义",
          "children": [{
            "name": "仗义",
            "children": [{
              "name": "仗义",
              "children": [{
                "name": "仗义",
                "children": []
              }]
            }, {
              "name": "仗义",
              "children": [{
                "name": "仗义",
                "children": []
              }]
            }, {
              "name": "仗义",
              "children": [{
                "name": "仗义",
                "children": []
              }]
            }, {"name": "仗义",
              "children": [{
                "name": "仗义",
                "children": []
              }]

            }]
          }]
        }]
      }]
    }]
  }, {
    "name": "仗义",
    "children": [{
      "name": "仗义",
      "children": [{
        "name": "仗义",
        "children": [{
          "name": "仗义",
          "children": []
        }]
      }, {
        "name": "仗义",
        "children": [{
          "name": "仗义",
          "children": [{
            "name": "仗义",
            "children": [{
              "name": "仗义",
              "children": []
            }]
          }, {
            "name": "仗义",
            "children": [{
              "name": "仗义",
              "children": []
            }]
          }]
        }]
      }, {
        "name": "仗义",
        "children": [{
          "name": "仗义",
          "children": []
        }]
      }]
    }]
  }, {
    "name": "仗义",
    "children": [{
      "name": "仗义",
      "children": []
    }]
  }]
}